{
  "tasks": [
    {
      "title": "Develop UI",
      "description": "Create the user interface using JavaFX.",
      "category": "Work",
      "priority": "High",
      "dueDate": "2024-12-20",
      "status": "DELAYED",
      "reminders": [
        { "reminderDate": "2025-02-20", "message": "default", "auto": true },
        { "reminderDate": "2025-02-26", "message": "default", "auto": true },
        { "reminderDate": "2024-12-19", "message": "UI deadline is tomorrow.", "auto": false }
      ]
    },
    {
      "title": "Bug Fixing",
      "description": "Fix critical bugs in the application.",
      "category": "Work",
      "priority": "Medium",
      "dueDate": "2024-12-22",
      "status": "IN_PROGRESS",
      "reminders": [
        { "reminderDate": "2025-02-20", "message": "default", "auto": true }
      ]
    },
    {
      "title": "Deployment Docs",
      "description": "Prepare documentation for deployment.",
      "category": "Documentation",
      "priority": "Low",
      "dueDate": "2024-12-25",
      "status": "OPEN",
      "reminders": []
    },
    {
      "title": "Write Documentation",
      "description": "Document new features and API changes.",
      "category": "Documentation",
      "priority": "Medium",
      "dueDate": "2024-12-28",
      "status": "POSTPONED",
      "reminders": [
        { "reminderDate": "2024-12-27", "message": "Finish writing documentation.", "auto": false }
      ]
    },
    {
      "title": "Update Project Plan",
      "description": "Revise the project plan and deadlines.",
      "category": "Planning",
      "priority": "High",
      "dueDate": "2024-12-30",
      "status": "OPEN",
      "reminders": [
        { "reminderDate": "2025-02-20", "message": "default", "auto": true },
        { "reminderDate": "2025-02-26", "message": "default", "auto": true }
      ]
    },
    {
      "title": "API Refactor",
      "description": "Refactor the backend APIs for better performance.",
      "category": "Backend",
      "priority": "High",
      "dueDate": "2025-01-10",
      "status": "DELAYED",
      "reminders": [
        { "reminderDate": "2025-02-20", "message": "default", "auto": true },
        { "reminderDate": "2025-02-26", "message": "default", "auto": true },
        { "reminderDate": "2025-01-28", "message": "default", "auto": true }
      ]
    },
    {
      "title": "Performance Tests",
      "description": "Run performance tests on new code.",
      "category": "Testing",
      "priority": "Medium",
      "dueDate": "2025-01-12",
      "status": "OPEN",
      "reminders": [
        { "reminderDate": "2025-02-20", "message": "default", "auto": true },
        { "reminderDate": "2025-01-11", "message": "Start performance tests.", "auto": false }
      ]
    },
    {
      "title": "UI Polish",
      "description": "Finalize UI design and fix layout issues.",
      "category": "Work",
      "priority": "High",
      "dueDate": "2025-01-08",
      "status": "OPEN",
      "reminders": [
        { "reminderDate": "2025-02-20", "message": "default", "auto": true },
        { "reminderDate": "2025-02-26", "message": "default", "auto": true }
      ]
    },
    {
      "title": "Database Migration",
      "description": "Migrate database schema to the new version.",
      "category": "Backend",
      "priority": "Low",
      "dueDate": "2025-01-01",
      "status": "COMPLETED",
      "reminders": []
    },
    {
      "title": "User Feedback Analysis",
      "description": "Review user feedback and prepare a summary report.",
      "category": "Research",
      "priority": "Medium",
      "dueDate": "2025-01-15",
      "status": "OPEN",
      "reminders": [
        { "reminderDate": "2025-01-14", "message": "Last day to gather feedback.", "auto": false }
      ]
    },
    {
      "title": "Security Audit",
      "description": "Perform a security audit on the entire application.",
      "category": "Security",
      "priority": "High",
      "dueDate": "2025-02-10",
      "status": "OPEN",
      "reminders": [
        { "reminderDate": "2025-02-09", "message": "Prepare security audit checklist.", "auto": false }
      ]
    },
    {
      "title": "Logo Redesign",
      "description": "Design a new logo for marketing materials.",
      "category": "Design",
      "priority": "Medium",
      "dueDate": "2025-01-25",
      "status": "OPEN",
      "reminders": [
        { "reminderDate": "2025-01-20", "message": "Show logo drafts to the marketing team.", "auto": false },
        { "reminderDate": "2025-01-24", "message": "Finalize logo design.", "auto": true }
      ]
    },
    {
      "title": "Client Presentation",
      "description": "Prepare slides and demos for the client presentation.",
      "category": "Meetings",
      "priority": "High",
      "dueDate": "2025-01-18",
      "status": "IN_PROGRESS",
      "reminders": [
        { "reminderDate": "2025-01-17", "message": "Rehearse final presentation.", "auto": false }
      ]
    },
    {
      "title": "Code Review",
      "description": "Review pull requests and provide feedback.",
      "category": "Work",
      "priority": "Medium",
      "dueDate": "2025-01-02",
      "status": "COMPLETED",
      "reminders": []
    },
    {
      "title": "Bug Triage",
      "description": "Go through bug backlog and prioritize.",
      "category": "Work",
      "priority": "Low",
      "dueDate": "2025-01-05",
      "status": "DELAYED",
      "reminders": [
        { "reminderDate": "2024-12-31", "message": "Start bug triage early.", "auto": false }
      ]
    },
    {
      "title": "Team Offsite Planning",
      "description": "Plan venue and agenda for team offsite meeting.",
      "category": "Meetings",
      "priority": "Low",
      "dueDate": "2025-02-01",
      "status": "OPEN",
      "reminders": [
        { "reminderDate": "2025-01-31", "message": "Confirm offsite venue.", "auto": true }
      ]
    },
    {
      "title": "Docker Setup",
      "description": "Set up Docker containers for staging environment.",
      "category": "Backend",
      "priority": "Medium",
      "dueDate": "2025-01-28",
      "status": "OPEN",
      "reminders": [
        { "reminderDate": "2025-01-27", "message": "Configure Docker settings.", "auto": true },
        { "reminderDate": "2025-01-28", "message": "Docker setup review.", "auto": false }
      ]
    },
    {
      "title": "Completed Task Example 1",
      "description": "Dummy completed task for testing.",
      "category": "General",
      "priority": "High",
      "dueDate": "2024-12-15",
      "status": "COMPLETED",
      "reminders": []
    },
    {
      "title": "Delayed Task Example 1",
      "description": "Dummy delayed task for demonstration.",
      "category": "General",
      "priority": "Medium",
      "dueDate": "2024-12-10",
      "status": "DELAYED",
      "reminders": [
        { "reminderDate": "2024-12-09", "message": "Task is about to be delayed!", "auto": false }
      ]
    },
    {
      "title": "Analytics Setup",
      "description": "Configure analytics tracking on the new website.",
      "category": "Research",
      "priority": "Medium",
      "dueDate": "2025-02-14",
      "status": "OPEN",
      "reminders": [
        { "reminderDate": "2025-02-13", "message": "Check analytics configuration.", "auto": true }
      ]
    },
    {
      "title": "Beta Release",
      "description": "Release the beta version to internal testers.",
      "category": "Work",
      "priority": "High",
      "dueDate": "2025-02-20",
      "status": "IN_PROGRESS",
      "reminders": [
        { "reminderDate": "2025-02-19", "message": "Send notifications to testers.", "auto": false }
      ]
    },
    {
      "title": "Mobile UI Testing",
      "description": "Test the UI on different mobile devices.",
      "category": "Testing",
      "priority": "Medium",
      "dueDate": "2025-02-22",
      "status": "OPEN",
      "reminders": [
        { "reminderDate": "2025-02-21", "message": "Ensure mobile compatibility.", "auto": false }
      ]
    },
    {
      "title": "User Training Video",
      "description": "Create a short video tutorial for new users.",
      "category": "Documentation",
      "priority": "Low",
      "dueDate": "2025-02-18",
      "status": "OPEN",
      "reminders": [
        { "reminderDate": "2025-02-17", "message": "Draft video script.", "auto": true }
      ]
    },
    {
      "title": "Code Cleanup",
      "description": "Remove deprecated methods and reorganize packages.",
      "category": "Work",
      "priority": "Low",
      "dueDate": "2025-02-05",
      "status": "OPEN",
      "reminders": [
        { "reminderDate": "2025-02-04", "message": "Last check for cleanup tasks.", "auto": false }
      ]
    },
    {
      "title": "Marketing Plan",
      "description": "Prepare a marketing plan for next quarter.",
      "category": "Planning",
      "priority": "Medium",
      "dueDate": "2025-02-28",
      "status": "OPEN",
      "reminders": [
        { "reminderDate": "2025-02-27", "message": "Finalize marketing strategy.", "auto": false }
      ]
    }
  ],
  "categories": [
    {
      "name": "Work",
      "tasks": [
        "Develop UI",
        "Bug Fixing",
        "UI Polish",
        "Bug Triage",
        "Beta Release",
        "Code Cleanup"
      ]
    },
    {
      "name": "Documentation",
      "tasks": [
        "Deployment Docs",
        "Write Documentation",
        "User Training Video"
      ]
    },
    {
      "name": "Planning",
      "tasks": [
        "Update Project Plan",
        "Marketing Plan"
      ]
    },
    {
      "name": "Backend",
      "tasks": [
        "API Refactor",
        "Database Migration",
        "Docker Setup"
      ]
    },
    {
      "name": "Testing",
      "tasks": [
        "Performance Tests",
        "Mobile UI Testing"
      ]
    },
    {
      "name": "Research",
      "tasks": [
        "User Feedback Analysis",
        "Analytics Setup"
      ]
    },
    {
      "name": "Security",
      "tasks": [
        "Security Audit"
      ]
    },
    {
      "name": "Design",
      "tasks": [
        "Logo Redesign"
      ]
    },
    {
      "name": "Meetings",
      "tasks": [
        "Client Presentation",
        "Team Offsite Planning"
      ]
    },
    {
      "name": "General",
      "tasks": [
        "Completed Task Example 1",
        "Delayed Task Example 1"
      ]
    }
  ],
  "priorities": [
    {
      "name": "High",
      "tasks": [
        "Develop UI",
        "Update Project Plan",
        "API Refactor",
        "UI Polish",
        "Security Audit",
        "Client Presentation",
        "Completed Task Example 1",
        "Beta Release"
      ]
    },
    {
      "name": "Medium",
      "tasks": [
        "Bug Fixing",
        "Write Documentation",
        "Performance Tests",
        "User Feedback Analysis",
        "Logo Redesign",
        "Delayed Task Example 1",
        "Docker Setup",
        "Marketing Plan",
        "Analytics Setup"
      ]
    },
    {
      "name": "Low",
      "tasks": [
        "Deployment Docs",
        "Database Migration",
        "Bug Triage",
        "Team Offsite Planning",
        "Code Review",
        "User Training Video",
        "Code Cleanup"
      ]
    }
  ]
}
